{
  "items": [
    {
      "text": "Blog",
      "url": "/all-posts/",
      "section": "blog"
    },
    {
      "text": "Reading List",
      "section": "reading-list",
      "url": "/reading-list/"
    },
    {
      "text": "About me",
      "url": "/about/",
      "section": "about"
    },
    {
      "text": "Twitter",
      "url": "https://twitter.com/_edjw/"
    },
    {
      "text": "Github",
      "url": "https://github.com/edjw/"
    },
    {
      "text": "RSS",
      "url": "/feed.xml/"
    }
  ]
}
